movslib-0.0.1.dist-info/METADATA
movslib-0.0.1.dist-info/WHEEL
movslib-0.0.1.dist-info/entry_points.txt
movslib/__init__.py
movslib/estrattoconto/__init__.py
movslib/estrattoconto/template_1.json
movslib/estrattoconto/template_2.json
movslib/estrattoconto/template_3.json
movslib/iterhelper.py
movslib/libretto.py
movslib/model.py
movslib/movs.py
movslib/postepay.py
movslib/py.typed
movslib/scansioni.py
movslib-0.0.1.dist-info/RECORD
